OpenRacer/.gitignore
OpenRacer/Albert.npy
OpenRacer/Constants.py
OpenRacer/Interface.py
OpenRacer/Model.py
OpenRacer/Monaco.npy
OpenRacer/Recorder.py
OpenRacer/Routes.py
OpenRacer/Util.py
OpenRacer/__init__.py
OpenRacer/datatypes.py
OpenRacer/example.py
OpenRacer/docs/Makefile
OpenRacer/docs/OpenRacer.rst
OpenRacer/docs/conf.py
OpenRacer/docs/index.rst
OpenRacer/docs/make.bat
OpenRacer/docs/modules.rst
OpenRacer/docs/_build/.buildinfo
OpenRacer/docs/_build/OpenRacer.html
OpenRacer/docs/_build/genindex.html
OpenRacer/docs/_build/index.html
OpenRacer/docs/_build/modules.html
OpenRacer/docs/_build/objects.inv
OpenRacer/docs/_build/py-modindex.html
OpenRacer/docs/_build/search.html
OpenRacer/docs/_build/searchindex.js
OpenRacer/docs/_build/.doctrees/OpenRacer.doctree
OpenRacer/docs/_build/.doctrees/environment.pickle
OpenRacer/docs/_build/.doctrees/index.doctree
OpenRacer/docs/_build/.doctrees/modules.doctree
OpenRacer/docs/_build/_modules/index.html
OpenRacer/docs/_build/_modules/OpenRacer/Constants.html
OpenRacer/docs/_build/_modules/OpenRacer/Interface.html
OpenRacer/docs/_build/_modules/OpenRacer/Model.html
OpenRacer/docs/_build/_modules/OpenRacer/Recorder.html
OpenRacer/docs/_build/_modules/OpenRacer/Routes.html
OpenRacer/docs/_build/_modules/OpenRacer/Util.html
OpenRacer/docs/_build/_modules/OpenRacer/datatypes.html
OpenRacer/docs/_build/_modules/OpenRacer/example.html
OpenRacer/docs/_build/_sources/OpenRacer.rst.txt
OpenRacer/docs/_build/_sources/index.rst.txt
OpenRacer/docs/_build/_sources/modules.rst.txt
OpenRacer/docs/_build/_static/_sphinx_javascript_frameworks_compat.js
OpenRacer/docs/_build/_static/alabaster.css
OpenRacer/docs/_build/_static/background_b01.png
OpenRacer/docs/_build/_static/basic.css
OpenRacer/docs/_build/_static/bizstyle.css
OpenRacer/docs/_build/_static/bizstyle.js
OpenRacer/docs/_build/_static/classic.css
OpenRacer/docs/_build/_static/css3-mediaqueries.js
OpenRacer/docs/_build/_static/css3-mediaqueries_src.js
openracer-0.6.6.dist-info/METADATA
openracer-0.6.6.dist-info/WHEEL
openracer-0.6.6.dist-info/licenses/LICENSE
openracer-0.6.6.dist-info/RECORD
