Metadata-Version: 2.1
Name: OpenRacer
Version: 0.6.6
Summary: Package to connect with OpenRacer application.
Project-URL: Issues, https://github.com/Loony4Logic/OpenRacer/issues
Author-email: Hitansh Doshi <hkd159@gmail.com>
License-File: LICENSE
Classifier: Development Status :: 4 - Beta
Classifier: Environment :: Web Environment
Classifier: Framework :: FastAPI
Classifier: Intended Audience :: Developers
Classifier: Intended Audience :: Education
Classifier: Intended Audience :: Science/Research
Classifier: Natural Language :: English
Classifier: Operating System :: OS Independent
Classifier: Programming Language :: Python :: 3
Classifier: Topic :: Games/Entertainment :: Simulation
Classifier: Topic :: Scientific/Engineering :: Artificial Intelligence
Requires-Python: >=3.8
Requires-Dist: annotated-types==0.7.0
Requires-Dist: anyio==4.5.2
Requires-Dist: click==8.1.8
Requires-Dist: colorama==0.4.6
Requires-Dist: exceptiongroup==1.2.2
Requires-Dist: fastapi==0.115.11
Requires-Dist: h11==0.14.0
Requires-Dist: httptools==0.6.4
Requires-Dist: idna==3.10
Requires-Dist: markdown-it-py==3.0.0
Requires-Dist: mdurl==0.1.2
Requires-Dist: numpy==1.24.4
Requires-Dist: pydantic-core==2.27.2
Requires-Dist: pydantic==2.10.6
Requires-Dist: pygments==2.19.1
Requires-Dist: python-dotenv==1.0.1
Requires-Dist: pyyaml==6.0.2
Requires-Dist: rich==13.9.4
Requires-Dist: sniffio==1.3.1
Requires-Dist: starlette==0.44.0
Requires-Dist: typing-extensions==4.12.2
Requires-Dist: uvicorn==0.33.0
Requires-Dist: watchfiles==0.24.0
Requires-Dist: websockets==13.1
